{
    "backend": "api-server-nodejs",
    "db_name": "",
    "db_pass": "",
    "db_type": "sqlite",
    "db_user": "",
    "dbms": "1",
    "description": "generated product",
    "design": "material-kit",
    "docker": "1",
    "err_code": 0,
    "frontend": "react",
    "heroku": "0",
    "pattern": "fullstack",
    "pro": "0",
    "task_id": "7a10f864-8c2d-4c2a-a7ad-66d1ae0c735c",
    "task_info": "Upload Sources [0%] - 320 files",
    "task_output": "7a10f864-8c2d-4c2a-a7ad-66d1ae0c735c.zip",
    "task_result": "SUCCESS",
    "task_state": "RUNNING",
    "task_ts_end": "2023-06-01-19-07-41",
    "task_ts_start": "2023-06-01-19-07-39"
}